{"cameraMode":{"drawMode":0,"name":"Shaded","section":"Shading Mode"},"sceneLighting":true,"audioPlay":false,"sceneViewState":{"m_AlwaysRefresh":false,"showFog":true,"showSkybox":true,"showFlares":true,"showImageEffects":true,"showParticleSystems":true,"showVisualEffectGraphs":true,"m_FxEnabled":true},"in2DMode":false,"pivot":{"x":10.034520149230957,"y":59.10752487182617,"z":2.0745558738708498},"rotation":{"x":-0.17684128880500794,"y":-0.7955507040023804,"z":0.2753019332885742,"w":-0.5101394653320313},"size":5.7855000495910648,"orthographic":false}